procworld/__init__.py
procworld/biomes.py
procworld/generator.py
procworld/utils.py
procworld-0.1.0.dist-info/METADATA
procworld-0.1.0.dist-info/WHEEL
procworld-0.1.0.dist-info/top_level.txt
procworld-0.1.0.dist-info/RECORD
