Metadata-Version: 2.4
Name: procworld
Version: 0.1.0
Summary: Advanced Procedural World Generator library for Python with JSON and PNG export
Author-email: veliqq <veliqorg@proton.me>
License: MIT
Project-URL: Homepage, https://github.com/veliqq/procworld
Project-URL: Repository, https://github.com/veliqq/procworld
Classifier: Programming Language :: Python :: 3
Classifier: License :: OSI Approved :: MIT License
Classifier: Operating System :: OS Independent
Requires-Python: >=3.8
Provides-Extra: images
Requires-Dist: Pillow>=9.0.0; extra == "images"
